lintlens/__init__.py
lintlens/cli.py
lintlens/git.py
lintlens/linting.py
lintlens/utils.py
lintlens/lint/__init__.py
lintlens/lint/unix.py
lintlens/tests/__init__.py
lintlens/tests/test_git.py
lintlens/tests/test_lint_unix.py
lintlens/tests/test_utils.py
lintlens-0.0.7.dist-info/LICENSE.txt
lintlens-0.0.7.dist-info/METADATA
lintlens-0.0.7.dist-info/RECORD
lintlens-0.0.7.dist-info/WHEEL
lintlens-0.0.7.dist-info/entry_points.txt
lintlens-0.0.7.dist-info/top_level.txt
