Metadata-Version: 2.1
Name: lintlens
Version: 0.0.7
Summary: Filters lint report and keep only defects on changed lines
Home-page: https://github.com/draganHR/lintlens
Author: Dragan Bosnjak
License: UNKNOWN
Platform: UNKNOWN
Classifier: Programming Language :: Python
Classifier: Programming Language :: Python :: 2.7
Classifier: Programming Language :: Python :: 3.6
Provides-Extra: tests
Requires-Dist: six (>=1.9.0)
Provides-Extra: tests
Requires-Dist: pytest (>=3.7.0); extra == 'tests'
